cilog/__init__.py
cilog/api.py
cilog/definitions.py
cilog/formatter.py
cilog/handler.py
cilog/launcher.py
cilog/logger.py
cilog/scripts.py
cilog/utils.py
cilog-1.3.0.dist-info/LICENSE
cilog-1.3.0.dist-info/METADATA
cilog-1.3.0.dist-info/WHEEL
cilog-1.3.0.dist-info/entry_points.txt
cilog-1.3.0.dist-info/top_level.txt
cilog-1.3.0.dist-info/RECORD
