Metadata-Version: 2.1
Name: cilog
Version: 1.3.0
Summary: CiLog is a flexible integrated logging tool
Home-page: https://github.com/CM-BF/CiLog/
Author: Shurui Gui
Author-email: citrinegui@gmail.com
License: UNKNOWN
Platform: UNKNOWN
Classifier: Programming Language :: Python :: 3
Classifier: License :: OSI Approved :: MIT License
Classifier: Operating System :: OS Independent
Requires-Python: >=3.6
License-File: LICENSE
Requires-Dist: pandas
Requires-Dist: tabulate
Requires-Dist: openpyxl
